ss_toolz/__init__.py
sstools/__init__.py
3636c788d0392f7e84453434eea18c59-0.0.5.dist-info/LICENSE
3636c788d0392f7e84453434eea18c59-0.0.5.dist-info/METADATA
3636c788d0392f7e84453434eea18c59-0.0.5.dist-info/WHEEL
3636c788d0392f7e84453434eea18c59-0.0.5.dist-info/top_level.txt
3636c788d0392f7e84453434eea18c59-0.0.5.dist-info/RECORD
