Metadata-Version: 2.1
Name: 3636c788d0392f7e84453434eea18c59
Version: 0.0.5
Summary: Confidential
Home-page: UNKNOWN
Author: Sarang Purandare
Author-email: purandare.sarang@gmail.com
License: UNKNOWN
Platform: UNKNOWN
Classifier: Programming Language :: Python :: 3
Requires-Dist: pandas
Requires-Dist: requests
Requires-Dist: ipython
Requires-Dist: plotly
